fxscript/__init__.py
fxscript-0.0.0.dist-info/DESCRIPTION.rst
fxscript-0.0.0.dist-info/METADATA
fxscript-0.0.0.dist-info/RECORD
fxscript-0.0.0.dist-info/WHEEL
fxscript-0.0.0.dist-info/metadata.json
fxscript-0.0.0.dist-info/top_level.txt
