Metadata-Version: 2.0
Name: fxscript
Version: 0.0.0
Summary: FX Script
Home-page: UNKNOWN
Author: UNKNOWN
Author-email: UNKNOWN
License: GNU General Public License v3
Platform: UNKNOWN
